fullmoon/__init__.py
fullmoon/is_full_moon.py
fullmoon/next_full_moon.py
fullmoon-1.0.2.dist-info/METADATA
fullmoon-1.0.2.dist-info/RECORD
fullmoon-1.0.2.dist-info/WHEEL
fullmoon-1.0.2.dist-info/top_level.txt
