Metadata-Version: 2.1
Name: fullmoon
Version: 1.0.2
Summary: Determine the occurrence of the next full moon or to determine if a given date is/was/will be a full moon.
Home-page: https://github.com/jr-k/python-fullmoon
Author: jrk
License: MIT
Platform: any
Classifier: License :: OSI Approved :: MIT License
Classifier: Operating System :: OS Independent
Classifier: Programming Language :: Python :: 3
Classifier: Programming Language :: Python :: 3.5
Classifier: Programming Language :: Python :: 3.6
Classifier: Programming Language :: Python :: 3.7
Classifier: Programming Language :: Python :: 3.8
Classifier: Programming Language :: Python :: Implementation :: PyPy
Classifier: Topic :: Office/Business :: Scheduling
Classifier: Topic :: Software Development :: Libraries :: Python Modules
